wws/__init__.py
wws/commands/__init__.py
wws/commands/add.py
wws/commands/agent.py
wws/commands/ls.py
wws/commands/rm.py
wws/commands/sync.py
wws/commands/utils.py
wws/wws.py
wws-0.1.12.dist-info/entry_points.txt
wws-0.1.12.dist-info/LICENSE
wws-0.1.12.dist-info/WHEEL
wws-0.1.12.dist-info/METADATA
wws-0.1.12.dist-info/RECORD
